collective.iconifiedcategory-0.71-py3.12-nspkg.pth
collective/iconifiedcategory/__init__.py
collective/iconifiedcategory/adapter.py
collective/iconifiedcategory/adapter.zcml
collective/iconifiedcategory/config.py
collective/iconifiedcategory/configure.zcml
collective/iconifiedcategory/event.py
collective/iconifiedcategory/indexes.py
collective/iconifiedcategory/interfaces.py
collective/iconifiedcategory/safe_utils.py
collective/iconifiedcategory/setuphandlers.py
collective/iconifiedcategory/testing-adapters.zcml
collective/iconifiedcategory/testing.py
collective/iconifiedcategory/upgrades.py
collective/iconifiedcategory/upgrades.zcml
collective/iconifiedcategory/utils.py
collective/iconifiedcategory/vocabularies.py
collective/iconifiedcategory/behaviors/__init__.py
collective/iconifiedcategory/behaviors/configure.zcml
collective/iconifiedcategory/behaviors/iconifiedcategorization.py
collective/iconifiedcategory/browser/__init__.py
collective/iconifiedcategory/browser/actionview.py
collective/iconifiedcategory/browser/config.py
collective/iconifiedcategory/browser/configure.zcml
collective/iconifiedcategory/browser/contentview.py
collective/iconifiedcategory/browser/controlpanel.py
collective/iconifiedcategory/browser/css.py
collective/iconifiedcategory/browser/subtyper.py
collective/iconifiedcategory/browser/tabview.py
collective/iconifiedcategory/browser/viewlets.py
collective/iconifiedcategory/browser/views.py
collective/iconifiedcategory/browser/static/.gitkeep
collective/iconifiedcategory/browser/static/iconifiedcategory.css
collective/iconifiedcategory/browser/static/iconifiedcategory.js
collective/iconifiedcategory/browser/static/images/more_infos.png
collective/iconifiedcategory/browser/templates/categorized-child-viewlet.pt
collective/iconifiedcategory/browser/templates/categorized-childs-infos.pt
collective/iconifiedcategory/browser/templates/categorized-childs-manage.pt
collective/iconifiedcategory/browser/templates/categorized-childs.pt
collective_iconifiedcategory-0.71.dist-info/METADATA
collective_iconifiedcategory-0.71.dist-info/WHEEL
collective_iconifiedcategory-0.71.dist-info/entry_points.txt
collective_iconifiedcategory-0.71.dist-info/namespace_packages.txt
collective_iconifiedcategory-0.71.dist-info/top_level.txt
collective_iconifiedcategory-0.71.dist-info/RECORD
