Metadata-Version: 2.4
Name: collective.iconifiedcategory
Version: 0.71
Summary: An add-on for Plone
Home-page: https://pypi.python.org/pypi/collective.iconifiedcategory
Author: IMIO
Author-email: support@imio.be
License: GPL version 2
Keywords: Python Plone
Classifier: Development Status :: 6 - Mature
Classifier: Environment :: Web Environment
Classifier: Framework :: Plone
Classifier: Framework :: Plone :: 4.3
Classifier: Programming Language :: Python
Classifier: Programming Language :: Python :: 2.7
Classifier: Operating System :: OS Independent
Classifier: License :: OSI Approved :: GNU General Public License v2 (GPLv2)
Requires-Dist: collective.documentviewer<5
Requires-Dist: collective.eeafaceted.z3ctable>2.17
Requires-Dist: collective.fontawesome>=1.1
Requires-Dist: collective.js.tooltipster>0.1
Requires-Dist: collective.z3cform.select2
Requires-Dist: imio.helpers>=0.75
Requires-Dist: natsort
Requires-Dist: plone.api>=1.4.11
Requires-Dist: plone.app.contenttypes
Requires-Dist: plone.app.dexterity
Requires-Dist: plone.autoform
Requires-Dist: plone.formwidget.namedfile
Requires-Dist: plone.namedfile
Requires-Dist: setuptools
Requires-Dist: z3c.jbot
Requires-Dist: z3c.json
Requires-Dist: z3c.table
Provides-Extra: test
Requires-Dist: plone.app.testing; extra == "test"
Requires-Dist: plone.app.contenttypes; extra == "test"
Requires-Dist: plone.app.robotframework[debug]; extra == "test"
Dynamic: author
Dynamic: author-email
Dynamic: classifier
Dynamic: description
Dynamic: home-page
Dynamic: keywords
Dynamic: license
Dynamic: provides-extra
Dynamic: requires-dist
Dynamic: summary
